rooq/__init__.py
rooq/app.py
rooq/templates/index.html
rooq-0.1.2.dist-info/LICENSE
rooq-0.1.2.dist-info/METADATA
rooq-0.1.2.dist-info/WHEEL
rooq-0.1.2.dist-info/entry_points.txt
rooq-0.1.2.dist-info/top_level.txt
rooq-0.1.2.dist-info/RECORD
