Metadata-Version: 2.1
Name: rooq
Version: 0.1.2
Summary: automatically create files/folders according to provided structure
Home-page: https://github.com/naserjamal/rooq
Author: Naser Jamal
Author-email: naser.dll@hotmail.com
License: MIT
Platform: UNKNOWN
Classifier: Programming Language :: Python :: 3
Classifier: License :: OSI Approved :: MIT License
Classifier: Operating System :: OS Independent
License-File: LICENSE
Requires-Dist: Flask
